timeweather/__init__.py
timeweather/pyweather.py
timeweather-0.1.0.dist-info/METADATA
timeweather-0.1.0.dist-info/WHEEL
timeweather-0.1.0.dist-info/top_level.txt
timeweather-0.1.0.dist-info/RECORD
