Metadata-Version: 2.1
Name: timeweather
Version: 0.1.0
Summary: Weather API Lib
Home-page: UNKNOWN
Author: TimeStudio
Author-email: sjgzszg@163.com
License: MIT
Platform: UNKNOWN
